[
  {
    "id": 4175,
    "title": "Kathy",
    "color": "pink"
  },
  {
    "id": 5941,
    "title": "John and Ryuuji",
    "color": "green"
  },
  {
    "id": 3195,
    "title": "john",
    "color": "blue"
  },
  {
    "id": 2677,
    "title": "Home",
    "color": "Red"
  },
  {
    "id": 8332,
    "title": "Home of life",
    "color": "Purple"
  },
  {
    "id": 404,
    "title": "Home of lies",
    "color": "Brown"
  },
  {
    "id": 2418,
    "title": "HEL",
    "color": "RED"
  },
  {
    "id": 8083,
    "title": "World of lies",
    "color": "Pink"
  },
  {
    "id": 8636,
    "title": "New way",
    "color": "Red"
  },
  {
    "id": 2310,
    "title": "New life",
    "color": "Red"
  },
  {
    "id": 4619,
    "title": "Day and night",
    "color": "Green"
  }
]